tlaplus_state_graph_utils/__init__.py
tlaplus_state_graph_utils/py.typed
tlaplus_state_graph_utils/cli/__init__.py
tlaplus_state_graph_utils/cli/convert.py
tlaplus_state_graph_utils/cli/root.py
tlaplus_state_graph_utils/format_determination/__init__.py
tlaplus_state_graph_utils/format_determination/formats.py
tlaplus_state_graph_utils/format_determination/utils/__init__.py
tlaplus_state_graph_utils/format_determination/utils/io.py
tlaplus_state_graph_utils/graph/__init__.py
tlaplus_state_graph_utils/graph/any_to_model.py
tlaplus_state_graph_utils/graph/dot_json_to_model.py
tlaplus_state_graph_utils/graph/dot_json_to_reasonable_json.py
tlaplus_state_graph_utils/graph/model.py
tlaplus_state_graph_utils/graph/model_to_d2.py
tlaplus_state_graph_utils/graph/model_to_reasonable_json.py
tlaplus_state_graph_utils/graph/reasonable_json_to_model.py
tlaplus_state_graph_utils/state/__init__.py
tlaplus_state_graph_utils/state/model.py
tlaplus_state_graph_utils/state/model_to_d2.py
tlaplus_state_graph_utils/state/model_to_itf.py
tlaplus_state_graph_utils/state/model_to_reasonable_json.py
tlaplus_state_graph_utils/state/model_to_simple_structured_json.py
tlaplus_state_graph_utils/state/tlaplus_to_latex.py
tlaplus_state_graph_utils/state/tlaplus_to_model.py
tlaplus_state_graph_utils/utils/__init__.py
tlaplus_state_graph_utils/utils/jsonish.py
tlaplus_state_graph_utils/utils/package_extras.py
tlaplus_state_graph_utils-0.2.0.dist-info/METADATA
tlaplus_state_graph_utils-0.2.0.dist-info/WHEEL
tlaplus_state_graph_utils-0.2.0.dist-info/entry_points.txt
tlaplus_state_graph_utils-0.2.0.dist-info/licenses/LICENSE
tlaplus_state_graph_utils-0.2.0.dist-info/RECORD
