Metadata-Version: 2.3
Name: tlaplus-state-graph-utils
Version: 0.2.0
Summary: Utilities for working with TLA+ state graphs
Project-URL: Repository, https://github.com/smheidrich/tlaplus-state-graph-utils.py
License-File: LICENSE
Requires-Python: >=3.12
Provides-Extra: d2
Requires-Dist: py-d2<2,>=1.0.1; extra == 'd2'
Requires-Dist: tree-sitter-tlaplus<2,>=1.3.6; extra == 'd2'
Requires-Dist: tree-sitter<0.24,>=0.23.0; extra == 'd2'
Provides-Extra: parse-state
Requires-Dist: tree-sitter-tlaplus<2,>=1.3.6; extra == 'parse-state'
Requires-Dist: tree-sitter<0.24,>=0.23.0; extra == 'parse-state'
